django_pg_simple_hll/__init__.py
django_pg_simple_hll/aggregate.py
django_pg_simple_hll/functions.py
django_pg_simple_hll/migrations/0001_initial.py
django_pg_simple_hll/migrations/0001_initial.reverse.sql
django_pg_simple_hll/migrations/0001_initial.sql
django_pg_simple_hll/migrations/0002_custom_hashing.py
django_pg_simple_hll/migrations/0002_custom_hashing.reverse.sql
django_pg_simple_hll/migrations/0002_custom_hashing.sql
django_pg_simple_hll/migrations/__init__.py
django_pg_simple_hll/py.typed
django_pg_simple_hll-0.3.1.dist-info/METADATA
django_pg_simple_hll-0.3.1.dist-info/WHEEL
django_pg_simple_hll-0.3.1.dist-info/licenses/LICENSE
django_pg_simple_hll-0.3.1.dist-info/RECORD
