Metadata-Version: 2.4
Name: django_pg_simple_hll
Version: 0.3.1
Summary: A low-privilege implementation of hyperloglog for django and postgres
License: MIT
License-File: LICENSE
Author: Beauhurst
Author-email: opensource@beauhurst.com
Requires-Python: >=3.10,<3.14
Classifier: Environment :: Web Environment
Classifier: Framework :: Django
Classifier: Framework :: Django :: 4.2
Classifier: Framework :: Django :: 5.0
Classifier: Framework :: Django :: 5.2
Classifier: License :: OSI Approved :: MIT License
Classifier: Operating System :: OS Independent
Classifier: Programming Language :: Python :: 3
Classifier: Programming Language :: Python :: 3.10
Classifier: Programming Language :: Python :: 3.11
Classifier: Programming Language :: Python :: 3.12
Classifier: Programming Language :: Python :: 3.13
Classifier: Programming Language :: Python :: 3 :: Only
Requires-Dist: Django (>=4.2)
Requires-Dist: psycopg2-binary (>=2.9.6,<3.0.0)
